tests/__init__.py
tests/test_xml_flatten.py
xml_flatten/__init__.py
xml_flatten/xml_flatten.py
xml_flatten-1.0.0.dist-info/METADATA
xml_flatten-1.0.0.dist-info/WHEEL
xml_flatten-1.0.0.dist-info/top_level.txt
xml_flatten-1.0.0.dist-info/RECORD
