Metadata-Version: 2.1
Name: xml-flatten
Version: 1.0.0
Summary: This is a package to flatten a nested xml data file.
Home-page: UNKNOWN
Author: Joy Maitra
License: MIT
Platform: UNKNOWN
